Metadata-Version: 1.0
Name: my-api
Version: 0.1.3
Summary: UNKNOWN
Home-page: https://github.com/li010101/myapi.git
Author: li010101
Author-email: liyaohui54@gmail.com
License: MIT Licence
Platform: UNKNOWN
